{
	"delta_shell": 0.000685,
	"delta_He": 0.000065,
	"outer_radius_fuel_tablet": 0.0038,
	"inner_radius_fuel_tablet": 0.00115,
	"fuel_el_step": 0.01275,
	"coolant_temp_in_K": 571.35,
	"coolant_temp_out_K": 602.05,
	"Cp": 5810,
	"coolant_lambda": 0.539,
	"fuel_lambda": 3.22,
	"He_lambda": 0.275,
	"shell_lambda": 19.3,
	"K_r_max": 1,
	"K_z": 1,
	"rho_coolant_avg": 700.49,
	"mu_coolant_avg": 0.0000538,
	"enthalpy_in": 1324380,
	"enthalpy_out": 1482950,
	"reactor_thermal_power": 3200,
	"height" : 3.730
}